README
setup.py
src/indeed_contactForm/__init__.py
src/indeed_contactForm/admin.py
src/indeed_contactForm/forms.py
src/indeed_contactForm/models.py
src/indeed_contactForm/tests.py
src/indeed_contactForm/testsettings.py
src/indeed_contactForm/urls.py
src/indeed_contactForm/views.py
src/indeed_contactForm.egg-info/PKG-INFO
src/indeed_contactForm.egg-info/SOURCES.txt
src/indeed_contactForm.egg-info/dependency_links.txt
src/indeed_contactForm.egg-info/requires.txt
src/indeed_contactForm.egg-info/top_level.txt