Metadata-Version: 1.0
Name: indeed-contactForm
Version: 1.0.1
Summary: A very simple Contact Form for django
Home-page: http://bitbucket.org
Author: Arne Weiss
Author-email: arne.weiss@udo.edu
License: GPLv2
Platform: UNKNOWN
Classifier: Framework :: Django
Classifier: Intended Audience :: Developers
Classifier: License :: OSI Approved :: GNU General Public License (GPL)
Classifier: Operating System :: OS Independent
Classifier: Programming Language :: Python
Classifier: Topic :: Internet :: WWW/HTTP
